pants_backend_oci-0.8.1.dist-info/METADATA
pants_backend_oci-0.8.1.dist-info/WHEEL
pants_backend_oci-0.8.1.dist-info/entry_points.txt
pants_backend_oci-0.8.1.dist-info/licenses/LICENSE-MIT.txt
pants_backend_oci/__init__.py
pants_backend_oci/goals/__init__.py
pants_backend_oci/goals/package.py
pants_backend_oci/goals/package_build_step.py
pants_backend_oci/goals/publish.py
pants_backend_oci/goals/run.py
pants_backend_oci/language_target/__init__.py
pants_backend_oci/language_target/python.py
pants_backend_oci/register.py
pants_backend_oci/rules/kustomize_inject.py
pants_backend_oci/subsystem.py
pants_backend_oci/synthetic_targets.py
pants_backend_oci/target_types.py
pants_backend_oci/targets.py
pants_backend_oci/tools/__init__.py
pants_backend_oci/tools/process.py
pants_backend_oci/util_rules/__init__.py
pants_backend_oci/util_rules/archive.py
pants_backend_oci/util_rules/binaries.py
pants_backend_oci/util_rules/build_image_artifact.py
pants_backend_oci/util_rules/build_image_bundle.py
pants_backend_oci/util_rules/configure.py
pants_backend_oci/util_rules/copy.py
pants_backend_oci/util_rules/empty_image_bundle.py
pants_backend_oci/util_rules/image_bundle.py
pants_backend_oci/util_rules/jq.py
pants_backend_oci/util_rules/layer.py
pants_backend_oci/util_rules/oci_sha.py
pants_backend_oci/util_rules/pull_image_bundle.py
pants_backend_oci/util_rules/run.py
pants_backend_oci/util_rules/tools.py
pants_backend_oci/util_rules/unpack.py
pants_backend_oci/utility/mirror/README.md
pants_backend_oci/utility/mirror/__init__.py
pants_backend_oci/utility/mirror/goals/__init__.py
pants_backend_oci/utility/mirror/goals/package.py
pants_backend_oci/utility/mirror/goals/publish.py
pants_backend_oci/utility/mirror/register.py
pants_backend_oci/utility/mirror/targets.py
pants_backend_oci-0.8.1.dist-info/RECORD
