Metadata-Version: 2.1
Name: pants_backend_oci
Version: 0.8.1
Summary: An OCI plugin for the Pants build system
Keywords: pantsbuild,pants,docker,oci,container
Author-Email: Tom Solberg <me@sbg.dev>
License: MIT License
Classifier: Development Status :: 4 - Beta
Classifier: Programming Language :: Python
Classifier: Topic :: Software Development :: Build Tools
Project-URL: Repository, https://github.com/tgolsson/pants-backends
Project-URL: Code, https://github.com/tgolsson/pants-backends/tree/main/pants-plugins/oci
Project-URL: Changelog, https://github.com/tgolsson/pants-backends/tree/main/pants-plugins/oci/CHANGELOG.md
Requires-Dist: pants-backend-kustomize>=0.2
